helpstack/__init__.py
helpstack/_nbdev.py
helpstack/help_stack.py
helpstack/warn_stack.py
helpstack-0.0.1.dist-info/LICENSE
helpstack-0.0.1.dist-info/METADATA
helpstack-0.0.1.dist-info/WHEEL
helpstack-0.0.1.dist-info/entry_points.txt
helpstack-0.0.1.dist-info/top_level.txt
helpstack-0.0.1.dist-info/RECORD
