Metadata-Version: 2.1
Name: helpstack
Version: 0.0.1
Summary: Library to reduce debugging time for developers using ipython notebooks (like jupyter notebook)
Home-page: https://github.com/nareshr8/helpstack/tree/master/
Author: Naresh Rangan
Author-email: naresh.r.8@gmail.com
License: Apache Software License 2.0
Keywords: Developer Productivity
Platform: UNKNOWN
Classifier: Development Status :: 3 - Alpha
Classifier: Intended Audience :: Developers
Classifier: Natural Language :: English
Classifier: Programming Language :: Python :: 3.7
Classifier: Programming Language :: Python :: 3.8
Classifier: License :: OSI Approved :: Apache Software License
Requires-Python: >=3.7
License-File: LICENSE
Requires-Dist: ghapi
Requires-Dist: ipywidgets
